m365proxy/__init__.py
m365proxy/__main__.py
m365proxy/cli.py
m365proxy/config.py
m365proxy/auth/__init__.py
m365proxy/auth/auth.py
m365proxy/controllers/__init__.py
m365proxy/controllers/pop3.py
m365proxy/controllers/smtp.py
m365proxy/core/__init__.py
m365proxy/core/graph_api.py
m365proxy/core/mail_queue.py
m365proxy/core/pop3.py
m365proxy/core/smtp.py
m365proxy/handlers/__init__.py
m365proxy/handlers/pop3.py
m365proxy/handlers/smtp.py
m365proxy/helpers/__init__.py
m365proxy/helpers/configure.py
m365proxy/helpers/graph_helper.py
m365proxy/utils/__init__.py
m365proxy/utils/shutdown.py
m365proxy/utils/utils.py
m365proxy/workers/__init__.py
m365proxy/workers/queue.py
m365proxy/workers/refresh_token.py
m365proxy-2.2.6.dist-info/licenses/LICENSE
m365proxy-2.2.6.dist-info/METADATA
m365proxy-2.2.6.dist-info/WHEEL
m365proxy-2.2.6.dist-info/entry_points.txt
m365proxy-2.2.6.dist-info/top_level.txt
m365proxy-2.2.6.dist-info/RECORD
