Metadata-Version: 2.4
Name: m365proxy
Version: 2.2.6
Summary: Lightweight SMTP and POP3 mail proxy to Microsoft 365 
Home-page: https://github.com/sh0rch/m365proxy
Author: sh0rch
Author-email: sh0rch@iwl.dev
License: MIT
Keywords: m365 smtp pop3 smtps pop3s starttls proxy mail email graph
Requires-Python: >=3.9.7
License-File: LICENSE
Requires-Dist: httpx
Requires-Dist: aiosmtpd
Requires-Dist: python-dotenv
Requires-Dist: colorlog
Requires-Dist: bcrypt
Requires-Dist: cryptography
Requires-Dist: msal
Requires-Dist: pysocks
Requires-Dist: python-jose
Dynamic: author
Dynamic: author-email
Dynamic: description
Dynamic: description-content-type
Dynamic: home-page
Dynamic: keywords
Dynamic: license
Dynamic: license-file
Dynamic: requires-dist
Dynamic: requires-python
Dynamic: summary
